AUTHORS
LICENSE
MANIFEST.in
README.md
pyproject.toml
setup.cfg
setup.py
pybloomfilter3.egg-info/PKG-INFO
pybloomfilter3.egg-info/SOURCES.txt
pybloomfilter3.egg-info/dependency_links.txt
pybloomfilter3.egg-info/requires.txt
pybloomfilter3.egg-info/top_level.txt
src/MurmurHash3.c
src/MurmurHash3.h
src/bloomfilter.c
src/bloomfilter.h
src/cbloomfilter.pxd
src/md5.c
src/md5.h
src/mmapbitarray.c
src/mmapbitarray.h
src/primetester.c
src/primetester.h
src/pybloomfilter.c
src/pybloomfilter.pyx
src/superfast.h
tests/__init__.py
tests/accuracytest.py
tests/simpletest.py
tests/comparisons/__init__.py
tests/comparisons/accuracytest.py
tests/comparisons/speedtest.py