Metadata-Version: 2.4
Name: pybloomfilter3
Version: 0.7.1
Summary: A fast implementation of Bloom filter for Python 3 built on mmap
Author-email: Prashant Sinha <prashant@noop.pw>, David Stromberger <cavoq@proton.me>
License: MIT
Project-URL: Homepage, https://github.com/cavoq/pybloomfiltermmap3
Classifier: Development Status :: 4 - Beta
Classifier: Intended Audience :: Developers
Classifier: Intended Audience :: Science/Research
Classifier: Programming Language :: C
Classifier: Programming Language :: Cython
Classifier: Programming Language :: Python
Classifier: Programming Language :: Python :: 3
Classifier: Topic :: Software Development :: Libraries :: Python Modules
Requires-Python: <4,>=3.5
License-File: LICENSE
Provides-Extra: test
Requires-Dist: pytest; extra == "test"
Dynamic: license-file
